<?xml version="1.0" encoding="utf-8" standalone="yes"?>
<languages>
  <language name="English" id="en">
    
    <blocktypes>
      <!-- Disqus comments block -->
      <blocktype  name="CommentsBlock">
        <name>Disqus comments</name>
        <description>Allows to add Disqus comments on a page.</description>
      </blocktype>
    </blocktypes>

    <pagetypes>
      <common>
        <!-- Disqus comments block properties -->
        <property name="IsEnabled">
          <caption>Enable Disqus comments</caption>
          <help>Disqus comments are always enabled by default.</help>
        </property>
      </common>
    </pagetypes>    

    <disqus>

      <dynamiccontent>
        <displayname>Disqus comments</displayname>
        <description>Allows to add Disqus comments on a page.</description>
      </dynamiccontent>

    </disqus>
  </language>
</languages>
